[
  {
    "timestamp": "2026-04-22T18:49:54.533Z",
    "rounds": 35,
    "field": "800x600",
    "elapsed_ms": 10687,
    "bot_a": {
      "name": "xander.cat.XanderCat 12.9",
      "total_score": 2116,
      "score_pct": 100,
      "survival": 1750,
      "survival_bonus": 350,
      "bullet_damage": 16,
      "bullet_bonus": 0,
      "ram_damage": 0,
      "ram_bonus": 0,
      "firsts": 35,
      "seconds": 0,
      "thirds": 0
    },
    "bot_b": {
      "name": "cjm.chalk.Chalk 2.6.Be",
      "total_score": 0,
      "score_pct": 0,
      "survival": 0,
      "survival_bonus": 0,
      "bullet_damage": 0,
      "bullet_bonus": 0,
      "ram_damage": 0,
      "ram_bonus": 0,
      "firsts": 0,
      "seconds": 35,
      "thirds": 0
    },
    "record_file": "/__w/robocode-autopilot/robocode-autopilot/recordings/986f34d9.br"
  },
  {
    "timestamp": "2026-04-22T18:50:14.948Z",
    "rounds": 35,
    "field": "800x600",
    "elapsed_ms": 20404,
    "bot_a": {
      "name": "rsalesc.roborio.Roborio 1.2.4",
      "total_score": 3281,
      "score_pct": 64,
      "survival": 1400,
      "survival_bonus": 280,
      "bullet_damage": 1348,
      "bullet_bonus": 253,
      "ram_damage": 0,
      "ram_bonus": 0,
      "firsts": 28,
      "seconds": 7,
      "thirds": 0
    },
    "bot_b": {
      "name": "ags.Midboss 1q.fast",
      "total_score": 1869,
      "score_pct": 36,
      "survival": 350,
      "survival_bonus": 70,
      "bullet_damage": 1350,
      "bullet_bonus": 98,
      "ram_damage": 0,
      "ram_bonus": 0,
      "firsts": 7,
      "seconds": 28,
      "thirds": 0
    },
    "record_file": "/__w/robocode-autopilot/robocode-autopilot/recordings/6e3182e8.br"
  },
  {
    "timestamp": "2026-04-22T18:50:37.052Z",
    "rounds": 35,
    "field": "800x600",
    "elapsed_ms": 22103,
    "bot_a": {
      "name": "rsalesc.roborio.Roborio 1.2.4",
      "total_score": 2100,
      "score_pct": 100,
      "survival": 1750,
      "survival_bonus": 350,
      "bullet_damage": 0,
      "bullet_bonus": 0,
      "ram_damage": 0,
      "ram_bonus": 0,
      "firsts": 35,
      "seconds": 0,
      "thirds": 0
    },
    "bot_b": {
      "name": "kc.serpent.Hydra 0.21",
      "total_score": 1,
      "score_pct": 0,
      "survival": 0,
      "survival_bonus": 0,
      "bullet_damage": 1,
      "bullet_bonus": 0,
      "ram_damage": 0,
      "ram_bonus": 0,
      "firsts": 0,
      "seconds": 35,
      "thirds": 0
    },
    "record_file": "/__w/robocode-autopilot/robocode-autopilot/recordings/0dd615d6.br"
  },
  {
    "timestamp": "2026-04-22T18:52:17.934Z",
    "rounds": 35,
    "field": "800x600",
    "elapsed_ms": 100881,
    "bot_a": {
      "name": "voidious.Diamond 1.8.22",
      "total_score": 2967,
      "score_pct": 62,
      "survival": 1000,
      "survival_bonus": 200,
      "bullet_damage": 1544,
      "bullet_bonus": 223,
      "ram_damage": 0,
      "ram_bonus": 0,
      "firsts": 20,
      "seconds": 15,
      "thirds": 0
    },
    "bot_b": {
      "name": "rsalesc.roborio.Roborio 1.2.4",
      "total_score": 1853,
      "score_pct": 38,
      "survival": 750,
      "survival_bonus": 150,
      "bullet_damage": 846,
      "bullet_bonus": 107,
      "ram_damage": 0,
      "ram_bonus": 0,
      "firsts": 15,
      "seconds": 20,
      "thirds": 0
    },
    "record_file": "/__w/robocode-autopilot/robocode-autopilot/recordings/249117bd.br"
  },
  {
    "timestamp": "2026-04-22T18:52:30.071Z",
    "rounds": 35,
    "field": "800x600",
    "elapsed_ms": 12137,
    "bot_a": {
      "name": "abc.Shadow 3.83c",
      "total_score": 2562,
      "score_pct": 53,
      "survival": 700,
      "survival_bonus": 140,
      "bullet_damage": 1549,
      "bullet_bonus": 173,
      "ram_damage": 0,
      "ram_bonus": 0,
      "firsts": 14,
      "seconds": 21,
      "thirds": 0
    },
    "bot_b": {
      "name": "cb.Domogled 1.2",
      "total_score": 2265,
      "score_pct": 47,
      "survival": 1050,
      "survival_bonus": 210,
      "bullet_damage": 864,
      "bullet_bonus": 141,
      "ram_damage": 0,
      "ram_bonus": 0,
      "firsts": 21,
      "seconds": 14,
      "thirds": 0
    },
    "record_file": "/__w/robocode-autopilot/robocode-autopilot/recordings/e6f651de.br"
  },
  {
    "timestamp": "2026-04-22T18:52:51.978Z",
    "rounds": 35,
    "field": "800x600",
    "elapsed_ms": 21907,
    "bot_a": {
      "name": "rsalesc.roborio.Roborio 1.2.4",
      "total_score": 2590,
      "score_pct": 52,
      "survival": 1200,
      "survival_bonus": 240,
      "bullet_damage": 989,
      "bullet_bonus": 161,
      "ram_damage": 0,
      "ram_bonus": 0,
      "firsts": 24,
      "seconds": 11,
      "thirds": 0
    },
    "bot_b": {
      "name": "Krabb.sliNk.Garm 0.9u",
      "total_score": 2394,
      "score_pct": 48,
      "survival": 550,
      "survival_bonus": 110,
      "bullet_damage": 1583,
      "bullet_bonus": 151,
      "ram_damage": 0,
      "ram_bonus": 0,
      "firsts": 11,
      "seconds": 24,
      "thirds": 0
    },
    "record_file": "/__w/robocode-autopilot/robocode-autopilot/recordings/2c568dff.br"
  },
  {
    "timestamp": "2026-04-22T18:53:13.164Z",
    "rounds": 35,
    "field": "800x600",
    "elapsed_ms": 21185,
    "bot_a": {
      "name": "rsalesc.mega.Knight 0.6.28",
      "total_score": 2651,
      "score_pct": 53,
      "survival": 1150,
      "survival_bonus": 230,
      "bullet_damage": 1095,
      "bullet_bonus": 175,
      "ram_damage": 0,
      "ram_bonus": 0,
      "firsts": 23,
      "seconds": 12,
      "thirds": 0
    },
    "bot_b": {
      "name": "abc.Shadow 3.83c",
      "total_score": 2342,
      "score_pct": 47,
      "survival": 600,
      "survival_bonus": 120,
      "bullet_damage": 1480,
      "bullet_bonus": 143,
      "ram_damage": 0,
      "ram_bonus": 0,
      "firsts": 12,
      "seconds": 23,
      "thirds": 0
    },
    "record_file": "/__w/robocode-autopilot/robocode-autopilot/recordings/69911d9f.br"
  },
  {
    "timestamp": "2026-04-22T18:53:43.484Z",
    "rounds": 35,
    "field": "800x600",
    "elapsed_ms": 30320,
    "bot_a": {
      "name": "aaa.r.ScalarR 0.005h.053-noshield",
      "total_score": 2950,
      "score_pct": 63,
      "survival": 1300,
      "survival_bonus": 260,
      "bullet_damage": 1224,
      "bullet_bonus": 166,
      "ram_damage": 0,
      "ram_bonus": 0,
      "firsts": 26,
      "seconds": 9,
      "thirds": 0
    },
    "bot_b": {
      "name": "xander.cat.XanderCat 12.9",
      "total_score": 1770,
      "score_pct": 38,
      "survival": 450,
      "survival_bonus": 90,
      "bullet_damage": 1143,
      "bullet_bonus": 87,
      "ram_damage": 0,
      "ram_bonus": 0,
      "firsts": 9,
      "seconds": 26,
      "thirds": 0
    },
    "record_file": "/__w/robocode-autopilot/robocode-autopilot/recordings/cd143846.br"
  },
  {
    "timestamp": "2026-04-22T18:53:56.889Z",
    "rounds": 35,
    "field": "800x600",
    "elapsed_ms": 13405,
    "bot_a": {
      "name": "xander.cat.XanderCat 12.9",
      "total_score": 3174,
      "score_pct": 64,
      "survival": 1300,
      "survival_bonus": 260,
      "bullet_damage": 1386,
      "bullet_bonus": 227,
      "ram_damage": 0,
      "ram_bonus": 0,
      "firsts": 26,
      "seconds": 9,
      "thirds": 0
    },
    "bot_b": {
      "name": "zyx.mega.YersiniaPestis 3.0",
      "total_score": 1799,
      "score_pct": 36,
      "survival": 450,
      "survival_bonus": 90,
      "bullet_damage": 1168,
      "bullet_bonus": 91,
      "ram_damage": 0,
      "ram_bonus": 0,
      "firsts": 9,
      "seconds": 26,
      "thirds": 0
    },
    "record_file": "/__w/robocode-autopilot/robocode-autopilot/recordings/03cdc091.br"
  },
  {
    "timestamp": "2026-04-22T18:54:07.358Z",
    "rounds": 35,
    "field": "800x600",
    "elapsed_ms": 10469,
    "bot_a": {
      "name": "dsekercioglu.mega.Raven 3.56j8",
      "total_score": 2961,
      "score_pct": 60,
      "survival": 1150,
      "survival_bonus": 230,
      "bullet_damage": 1376,
      "bullet_bonus": 205,
      "ram_damage": 0,
      "ram_bonus": 0,
      "firsts": 23,
      "seconds": 12,
      "thirds": 0
    },
    "bot_b": {
      "name": "abc.Shadow 3.83c",
      "total_score": 2013,
      "score_pct": 40,
      "survival": 600,
      "survival_bonus": 120,
      "bullet_damage": 1164,
      "bullet_bonus": 127,
      "ram_damage": 1,
      "ram_bonus": 0,
      "firsts": 12,
      "seconds": 23,
      "thirds": 0
    },
    "record_file": "/__w/robocode-autopilot/robocode-autopilot/recordings/b9350613.br"
  }
]